dabax/__init__.py
dabax/common_tools.py
dabax/dabax_base.py
dabax/dabax_files.py
dabax/dabax_xraylib.py
dabax/dabax_xraylib_decorator.py
dabax-1.0.11.dist-info/licenses/LICENSE
dabax-1.0.11.dist-info/METADATA
dabax-1.0.11.dist-info/WHEEL
dabax-1.0.11.dist-info/top_level.txt
dabax-1.0.11.dist-info/RECORD
