Metadata-Version: 2.4
Name: dabax
Version: 1.0.11
Summary: python access to DABAX files
Home-page: https://github.com/oasys-kit/dabax/
Author: M Sanchez del Rio
Author-email: srio@esrf.eu
License-File: LICENSE
Requires-Dist: numpy
Requires-Dist: scipy
Requires-Dist: silx
Dynamic: author
Dynamic: author-email
Dynamic: description
Dynamic: description-content-type
Dynamic: home-page
Dynamic: license-file
Dynamic: requires-dist
Dynamic: summary
